pdf_appendix/__init__.py
pdf_appendix/cli.py
pdf_appendix/core.py
pdf_appendix-1.0.0.dist-info/licenses/LICENSE
pdf_appendix-1.0.0.dist-info/licenses/THIRD_PARTY_LICENSES
pdf_appendix-1.0.0.dist-info/METADATA
pdf_appendix-1.0.0.dist-info/WHEEL
pdf_appendix-1.0.0.dist-info/entry_points.txt
pdf_appendix-1.0.0.dist-info/top_level.txt
pdf_appendix-1.0.0.dist-info/RECORD
