Metadata-Version: 2.4
Name: pdf-appendix
Version: 1.0.0
Summary: A tool to merge appendices into a main PDF.
Author-email: Juan Jose Hasbun Wood <juan@hasbun-wood-engineering.de>
License-Expression: MIT
Project-URL: Source, https://github.com/HasbunWoodEngineering/pdf-appendix
Project-URL: Developer Homepage, https://hasbun-wood-engineering.de
Project-URL: License, https://github.com/HasbunWoodEngineering/pdf-appendix/blob/main/LICENSE
Project-URL: Third Party Licenses, https://github.com/HasbunWoodEngineering/pdf-appendix/blob/main/THIRD_PARTY_LICENSES
Keywords: pdf,appendix,merge,pypdf,cli
Classifier: Programming Language :: Python :: 3
Classifier: Operating System :: OS Independent
Requires-Python: >=3.9
License-File: LICENSE
License-File: THIRD_PARTY_LICENSES
Requires-Dist: pypdf>=6.0.0
Provides-Extra: dev
Requires-Dist: black>=24.0.0; extra == "dev"
Requires-Dist: pytest>=7.0; extra == "dev"
Requires-Dist: reportlab>=4.0.0; extra == "dev"
Dynamic: license-file
